{
  "version": "1.0.3",
  "buildId": "20260317-4",
  "releaseDate": "2026-03-17",
  "releaseTime": "19:56",
  "timezone": "Europe/Vienna",
  "note": "Wertguthaben-Status beim Speichern bewertet jetzt den aktuellen Restwert statt Eingabewert.",
  "commitId": "e083202",
  "obligation": "false",
  "history": [
    {
      "version": "1.0.3",
      "buildId": "20260317-4",
      "releaseDate": "2026-03-17",
      "releaseTime": "19:56",
      "note": "Wertguthaben-Status beim Speichern bewertet jetzt den aktuellen Restwert statt Eingabewert.",
      "commitId": "e083202",
      "obligation": "false"
    },
    {
      "version": "1.0.2",
      "buildId": "20260317-3",
      "releaseDate": "2026-03-17",
      "releaseTime": "18:17",
      "note": "Wertguthaben-Kategorie loeschen erfordert jetzt die Eingabe von LOESCHEN.",
      "commitId": "e083202",
      "obligation": "false"
    },
    {
      "version": "1.0.1",
      "buildId": "20260317-2",
      "releaseDate": "2026-03-17",
      "releaseTime": "18:12",
      "note": "Wertguthaben-Einstellungen: Kategorie kann nun auch per Enter hinzugefuegt werden.",
      "commitId": "e083202",
      "obligation": "false"
    },
    {
      "version": "1.0.0",
      "buildId": "20260317-1",
      "releaseDate": "2026-03-17",
      "releaseTime": "17:31",
      "note": "Update-Dialog mit Jetzt/Später und automatischer Versionspruefung aktiviert.",
      "commitId": "cde0a71e",
      "obligation": "false"
    }
  ]
}
